beautiful/__init__.py
beautiful/__version__.py
beautiful/py.typed
beautiful-0.0.1.dist-info/LICENSE
beautiful-0.0.1.dist-info/WHEEL
beautiful-0.0.1.dist-info/METADATA
beautiful-0.0.1.dist-info/RECORD
