Metadata-Version: 2.1
Name: beautiful
Version: 0.0.1
Summary:  collection of functions and classes to aid developers into building better code faster
Home-page: https://github.com/kalaspuff/beautiful
License: MIT
Keywords: beautiful
Author: Carl Oscar Aaro
Author-email: hello@carloscar.com
Requires-Python: >=3.6,<4.0
Classifier: Development Status :: 1 - Planning
Classifier: Intended Audience :: Developers
Classifier: License :: OSI Approved :: MIT License
Classifier: Programming Language :: Python
Classifier: Programming Language :: Python :: 3
Classifier: Programming Language :: Python :: 3.6
Classifier: Programming Language :: Python :: 3.7
Classifier: Programming Language :: Python :: 3.8
Classifier: Topic :: Software Development
Classifier: Topic :: Software Development :: Libraries
Classifier: Typing :: Typed
Project-URL: Repository, https://github.com/kalaspuff/beautiful
